README.md
setup.py
highway/__init__.py
highway/close_reasons.py
highway/converters.py
highway/data_types.py
highway/header.py
highway/log.py
highway/preparers.py
highway/routing.py
highway/utils.py
highway.py.egg-info/PKG-INFO
highway.py.egg-info/SOURCES.txt
highway.py.egg-info/dependency_links.txt
highway.py.egg-info/requires.txt
highway.py.egg-info/top_level.txt