Metadata-Version: 1.1
Name: highway.py
Version: 0.2.2
Summary: Asynchronous, route based, and data type preserving network protocol.
Home-page: https://github.com/PhilipTrauner/highway.py
Author: Philip Trauner
Author-email: philip.trauner@arztpraxis.io
License: MIT
Keywords: networking,asynchronous,data type preserving
Platform: UNKNOWN
Classifier: Development Status :: 4 - Beta
Classifier: Programming Language :: Python :: 3.6
Classifier: Intended Audience :: Developers
Classifier: License :: OSI Approved :: MIT License
